feeddiasp/Diasp.py
feeddiasp/FBParser.py
feeddiasp/FeedDiasp.py
feeddiasp/PostDBCSV.py
feeddiasp/RSSParser.py
feeddiasp/__init__.py
feeddiasp-0.2.0.dist-info/LICENSE
feeddiasp-0.2.0.dist-info/METADATA
feeddiasp-0.2.0.dist-info/WHEEL
feeddiasp-0.2.0.dist-info/top_level.txt
feeddiasp-0.2.0.dist-info/RECORD
