Metadata-Version: 2.1
Name: feeddiasp
Version: 0.2.0
Summary: Feed Diaspora with RSS-Feeds or Facebook
Home-page: https://github.com/Debakel/feedDiasp/
Author: Moritz Duchêne
Author-email: UNKNOWN
License: GPL
Keywords: diaspora facebook bot rss
Platform: UNKNOWN
Classifier: Programming Language :: Python :: 3
Requires-Dist: facepy
Requires-Dist: argparse
Requires-Dist: diaspy-api
Requires-Dist: feedparser
Requires-Dist: html2text
Requires-Dist: pypandoc
Requires-Dist: requests
